fastapi_sa_manager/__init__.py
fastapi_sa_manager/schemas.py
fastapi_sa_manager/services.py
fastapi_sa_manager-0.1.2.dist-info/LICENSE.md
fastapi_sa_manager-0.1.2.dist-info/METADATA
fastapi_sa_manager-0.1.2.dist-info/WHEEL
fastapi_sa_manager-0.1.2.dist-info/top_level.txt
fastapi_sa_manager-0.1.2.dist-info/RECORD
